odoo/addons/sale_order_carrier_auto_assign/README.rst
odoo/addons/sale_order_carrier_auto_assign/__init__.py
odoo/addons/sale_order_carrier_auto_assign/__manifest__.py
odoo/addons/sale_order_carrier_auto_assign/i18n/es.po
odoo/addons/sale_order_carrier_auto_assign/i18n/sale_order_carrier_auto_assign.pot
odoo/addons/sale_order_carrier_auto_assign/models/__init__.py
odoo/addons/sale_order_carrier_auto_assign/models/sale_order.py
odoo/addons/sale_order_carrier_auto_assign/readme/CONTRIBUTORS.rst
odoo/addons/sale_order_carrier_auto_assign/readme/CREDITS.rst
odoo/addons/sale_order_carrier_auto_assign/readme/DESCRIPTION.rst
odoo/addons/sale_order_carrier_auto_assign/static/description/icon.png
odoo/addons/sale_order_carrier_auto_assign/static/description/index.html
odoo/addons/sale_order_carrier_auto_assign/tests/__init__.py
odoo/addons/sale_order_carrier_auto_assign/tests/test_sale_order_carrier_auto_assign.py
odoo14_addon_sale_order_carrier_auto_assign-14.0.1.0.1.dist-info/METADATA
odoo14_addon_sale_order_carrier_auto_assign-14.0.1.0.1.dist-info/WHEEL
odoo14_addon_sale_order_carrier_auto_assign-14.0.1.0.1.dist-info/top_level.txt
odoo14_addon_sale_order_carrier_auto_assign-14.0.1.0.1.dist-info/RECORD
